README.md
setup.py
setup_proxy.py
http_proxy.egg-info/PKG-INFO
http_proxy.egg-info/SOURCES.txt
http_proxy.egg-info/dependency_links.txt
http_proxy.egg-info/entry_points.txt
http_proxy.egg-info/requires.txt
http_proxy.egg-info/top_level.txt
proxycore/__init__.py
proxycore/flows/__init__.py
proxycore/flows/duck_flow.py
proxycore/flows/narwhals_flow.py
proxycore/flows/zz_default_recipe.py
proxycore/parser/__init__.py
proxycore/parser/http_parser.py
proxycore/parser/parser_utils.py
proxycore/pipe/__init__.py
proxycore/pipe/apipe.py
proxycore/pipe/aserver.py
proxycore/pipe/communication.py
proxycore/pipe/endpoint.py
proxycore/pipe/importing.py
proxycore/pipe/logger.py
proxycore/pipe/persistence.py
proxycore/pipe/reporting.py
proxycore/pipe/recipe/__init__.py
proxycore/pipe/recipe/flow.py
proxycore/pipe/recipe/flow_finder.py
proxycore/pipe/recipe/matchers.py
proxycore/pipe/recipe/soap.py
proxycore/utils/__init__.py
proxycore/utils/soap2python.py
test/test_dispatcher.py
test/test_flow_definition.py
test/test_http_parser.py
test/test_persistence.py
test/test_soap_matcher.py
test/test_soap_transform.py
test/test_transform.py