Metadata-Version: 1.0
Name: http-proxy
Version: 1.0.13
Summary: HTTP reverse proxy for debugging and packet manipulation - Core and CLI
Home-page: https://github.com/xRodney/pyproxy
Author: Dusan Jakub
Author-email: UNKNOWN
License: UNKNOWN
Platform: UNKNOWN
